{
 "avg": {
  "C": "三口刀十五",
  "1B": "拉芙三特利",
  "2B": "十傑九",
  "3B": "獵魔女團",
  "SS": "洛杉磯拉拉",
  "LF": "八寶丹",
  "CF": "德祖",
  "RF": "李界領",
  "DH": "心月",
  "SP1": "億竑六",
  "SP2": "魔流劍",
  "SP3": "前健十",
  "SP4": "美好人生",
  "SP5": "賈斯汀五",
  "RP1": "基督是主四",
  "RP2": "寵兒魔女",
  "RP3": "蟲蟲十二世",
  "CP": "姆巴佩"
 },
 "hr": {
  "C": "小郭四一代",
  "1B": "雨後橫虹",
  "2B": "十傑九",
  "3B": "獵魔女團",
  "SS": "洛杉磯拉拉",
  "LF": "無名改十一",
  "CF": "天二五天",
  "RF": "請假王",
  "DH": "泡泡堂糖",
  "SP1": "億竑六",
  "SP2": "魔流劍",
  "SP3": "美好人生",
  "SP4": "前健十",
  "SP5": "賈斯汀五",
  "RP1": "基督是主四",
  "RP2": "寵兒魔女",
  "RP3": "蟲蟲十二世",
  "CP": "姆巴佩"
 },
 "rbi": {
  "C": "小郭四一代",
  "1B": "雨後橫虹",
  "2B": "十傑九",
  "3B": "獵魔女團",
  "SS": "洛杉磯拉拉",
  "LF": "無名改十一",
  "CF": "森亞露露卡",
  "RF": "請假王",
  "DH": "泡泡堂糖",
  "SP1": "億竑六",
  "SP2": "魔流劍",
  "SP3": "美好人生",
  "SP4": "前健十",
  "SP5": "賈斯汀五",
  "RP1": "基督是主四",
  "RP2": "寵兒魔女",
  "RP3": "蟲蟲十二世",
  "CP": "姆巴佩"
 },
 "sb": {
  "C": "小鷗神",
  "1B": "悍將五世",
  "2B": "梯歐歪立二",
  "3B": "老弱殘兵一",
  "SS": "亞特漾漾",
  "LF": "靜靜",
  "CF": "柯比氣氣",
  "RF": "重力強",
  "DH": "轟雷市十二",
  "SP1": "億竑六",
  "SP2": "魔流劍",
  "SP3": "美好人生",
  "SP4": "前健十",
  "SP5": "賈斯汀五",
  "RP1": "基督是主四",
  "RP2": "寵兒魔女",
  "RP3": "蟲蟲十二世",
  "CP": "姆巴佩"
 },
 "era": {
  "C": "小郭四一代",
  "1B": "雨後橫虹",
  "2B": "十傑九",
  "3B": "獵魔女團",
  "SS": "洛杉磯拉拉",
  "LF": "無名改十一",
  "CF": "森亞露露卡",
  "RF": "請假王",
  "DH": "泡泡堂糖",
  "SP1": "億竑六",
  "SP2": "阿基拉十二",
  "SP3": "美好人生",
  "SP4": "咪咪醬二六",
  "SP5": "前健十",
  "RP1": "或躍在淵",
  "RP2": "千古一帝",
  "RP3": "銀河之晨曦",
  "CP": "業餘球評"
 },
 "w": {
  "C": "小郭四一代",
  "1B": "曠野",
  "2B": "十傑九",
  "3B": "獵魔女團",
  "SS": "洛杉磯拉拉",
  "LF": "無名改十一",
  "CF": "森亞露露卡",
  "RF": "請假王",
  "DH": "泡泡堂糖",
  "SP1": "億竑六",
  "SP2": "阿基拉十二",
  "SP3": "多里斯改三",
  "SP4": "美好人生",
  "SP5": "佐藤光",
  "RP1": "陳信二",
  "RP2": "千古一帝",
  "RP3": "蟲蟲十二世",
  "CP": "雀聖十八"
 },
 "sv": {
  "C": "小郭四一代",
  "1B": "雨後橫虹",
  "2B": "十傑九",
  "3B": "獵魔女團",
  "SS": "洛杉磯拉拉",
  "LF": "無名改十一",
  "CF": "森亞露露卡",
  "RF": "請假王",
  "DH": "泡泡堂糖",
  "SP1": "億竑六",
  "SP2": "魔流劍",
  "SP3": "前健十",
  "SP4": "美好人生",
  "SP5": "賈斯汀五",
  "RP1": "銀河之晨曦",
  "RP2": "千古一帝",
  "RP3": "或躍在淵",
  "CP": "一轉黃大強"
 },
 "k": {
  "C": "小郭四一代",
  "1B": "雨後橫虹",
  "2B": "十傑九",
  "3B": "獵魔女團",
  "SS": "洛杉磯拉拉",
  "LF": "無名改十一",
  "CF": "森亞露露卡",
  "RF": "請假王",
  "DH": "泡泡堂糖",
  "SP1": "億竑六",
  "SP2": "魔流劍",
  "SP3": "美好人生",
  "SP4": "前健十",
  "SP5": "賈斯汀五",
  "RP1": "基督是主四",
  "RP2": "寵兒魔女",
  "RP3": "蟲蟲十二世",
  "CP": "姆巴佩"
 }
}